dcg_analytics_log/__init__.py
dcg_analytics_log/data/__init__.py
dcg_analytics_log/data/reader.py
dcg_analytics_log/data/schema.py
dcg_analytics_log/data/statistics.py
dcg_analytics_log/monitoring/__init__.py
dcg_analytics_log/monitoring/meta_table.py
dcg_analytics_log/monitoring/mlflow_meta.py
dcg_analytics_log/report/__init__.py
dcg_analytics_log/report/delta.py
dcg_analytics_log/report/features.py
dcg_analytics_log/report/full_data.py
dcg_analytics_log/report/nbo.py
dcg_analytics_log/report/report.py
dcg_analytics_log/report/scores.py
dcg_analytics_log-0.0.2.dist-info/METADATA
dcg_analytics_log-0.0.2.dist-info/WHEEL
dcg_analytics_log-0.0.2.dist-info/top_level.txt
dcg_analytics_log-0.0.2.dist-info/RECORD
